[
  {
    "id": 1,
    "name": "Zapatilla Nike Air",
    "price": 100,
    "discount": 10,
    "category": "visited",
    "description": "Un diseño moderno y cómodo, perfecto para tu estilo.",
    "image": "zapatilla-de-miles.jpg"
  },
  {
    "id": 5,
    "name": "Zapatilla Nike Air",
    "description": "Incluye la cámara D3500, el objetivo zoom AF-P DX NIKKOR 18-55mm y el superteleobjetivo zoom compacto AF-P DX NIKKOR 70-300mm. Ambos objetivos enfocan de forma rápida y silenciosa, lo que resulta ideal para grabar metraje de vídeo sin que se escuche apenas el ruido del accionamiento.",
    "price": 53000,
    "discount": 2,
    "image": "zapatillas-correr-sobre-fondo-blanco_10541-635.avif",
    "category": "in-sale"
  },
  {
    "id": 6,
    "name": "Zapatilla Nike Air",
    "description": "Caminar nunca habia sido tan comodo,cuando uses estas zapatilla te sentiras como el rey del mundo",
    "price": 20999,
    "discount": 1,
    "image": "zapatillas-de-hombre-bridger.jpg",
    "category": "in-sale"
  }
]